ttlv/__init__.py
ttlv/cli.py
ttlv/ttlv.py
ttlv-0.6.0.dist-info/LICENSE.txt
ttlv-0.6.0.dist-info/METADATA
ttlv-0.6.0.dist-info/WHEEL
ttlv-0.6.0.dist-info/entry_points.txt
ttlv-0.6.0.dist-info/top_level.txt
ttlv-0.6.0.dist-info/RECORD
