Metadata-Version: 2.1
Name: ttlv
Version: 0.6.0
Summary: A useful cli tool to make webm videos uploadable greater than 60s in length.
Home-page: https://github.com/pawanpaudel93/tiktok-long-video
Author: Pawan Paudel
Author-email: pawanpaudel93@gmail.com
License: MIT
Keywords: ttlv tiktok-long-video
Platform: UNKNOWN
Classifier: License :: OSI Approved :: MIT License
Classifier: Development Status :: 3 - Alpha
Classifier: Programming Language :: Python :: 3
Classifier: Programming Language :: Python :: 3.6
Classifier: Programming Language :: Python :: 3.7
Classifier: Programming Language :: Python :: 3.8
Classifier: Operating System :: OS Independent
Requires-Python: >=3.0
